<?xml version="1.0" encoding="UTF-8"?>
<files psalm-version="4.13.1@5cf660f63b548ccd4a56f62d916ee4d6028e01a3">
  <file src="src/Mealz/AccountingBundle/Controller/AccountingAdminController.php">
    <InvalidNullableReturnType occurrences="1">
      <code>Profile</code>
    </InvalidNullableReturnType>
    <NullableReturnStatement occurrences="1">
      <code>$this-&gt;getDoctrine()-&gt;getManager()-&gt;find(Profile::class, $profileId)</code>
    </NullableReturnStatement>
  </file>
  <file src="src/Mealz/AccountingBundle/Controller/AccountingBookController.php">
    <InvalidScalarArgument occurrences="1">
      <code>0</code>
    </InvalidScalarArgument>
    <TooManyArguments occurrences="1">
      <code>create</code>
    </TooManyArguments>
    <UndefinedConstant occurrences="3">
      <code>PDF_PAGE_FORMAT</code>
      <code>PDF_PAGE_ORIENTATION</code>
      <code>PDF_UNIT</code>
    </UndefinedConstant>
  </file>
  <file src="src/Mealz/AccountingBundle/Controller/CostSheetController.php">
    <InvalidArgument occurrences="3">
      <code>$receiver</code>
      <code>$secret</code>
      <code>$this-&gt;getParameter('app.base_url')</code>
    </InvalidArgument>
  </file>
  <file src="src/Mealz/AccountingBundle/Controller/Payment/CashController.php">
    <InvalidDocblock occurrences="1"/>
    <MissingDocblockType occurrences="1">
      <code>$participation</code>
    </MissingDocblockType>
  </file>
  <file src="src/Mealz/AccountingBundle/Entity/TransactionRepository.php">
    <UndefinedDocblockClass occurrences="1">
      <code>\Doctrine\DBAL\DBALException</code>
    </UndefinedDocblockClass>
  </file>
  <file src="src/Mealz/AccountingBundle/ParticipantList/ParticipantList.php">
    <InvalidReturnStatement occurrences="1">
      <code>$price</code>
    </InvalidReturnStatement>
    <InvalidReturnType occurrences="1">
      <code>int</code>
    </InvalidReturnType>
  </file>
  <file src="src/Mealz/AccountingBundle/Service/Wallet.php">
    <InvalidReturnStatement occurrences="1">
      <code>bcsub($transactions, $costs, 2)</code>
    </InvalidReturnStatement>
    <InvalidReturnType occurrences="1">
      <code>float</code>
    </InvalidReturnType>
    <InvalidScalarArgument occurrences="2">
      <code>$costs</code>
      <code>$transactions</code>
    </InvalidScalarArgument>
  </file>
  <file src="src/Mealz/AccountingBundle/Tests/Controller/AccountingBookControllerTest.php">
    <InvalidScalarArgument occurrences="1">
      <code>0</code>
    </InvalidScalarArgument>
    <UndefinedInterfaceMethod occurrences="4">
      <code>clear</code>
      <code>clear</code>
      <code>clear</code>
      <code>findUserDataAndTransactionAmountForGivenPeriod</code>
    </UndefinedInterfaceMethod>
  </file>
  <file src="src/Mealz/AccountingBundle/Tests/Controller/CostSheetControllerTest.php">
    <UndefinedInterfaceMethod occurrences="2">
      <code>getTotalAmount</code>
      <code>getTotalAmount</code>
    </UndefinedInterfaceMethod>
  </file>
  <file src="src/Mealz/AccountingBundle/Tests/Service/PayPal/PayPalServiceTest.php">
    <TooManyArguments occurrences="3">
      <code>willReturn</code>
      <code>willReturn</code>
      <code>willReturn</code>
    </TooManyArguments>
  </file>
  <file src="src/Mealz/AccountingBundle/Tests/Service/TransactionServiceTest.php">
    <TooManyArguments occurrences="2">
      <code>willReturn</code>
      <code>willReturn</code>
    </TooManyArguments>
  </file>
  <file src="src/Mealz/MealBundle/Controller/BaseController.php">
    <InvalidParamDefault occurrences="1">
      <code>bool</code>
    </InvalidParamDefault>
    <InvalidScalarArgument occurrences="1">
      <code>$referenceType</code>
    </InvalidScalarArgument>
  </file>
  <file src="src/Mealz/MealBundle/Controller/BaseListController.php">
    <FalsableReturnStatement occurrences="1">
      <code>$renderedForm-&gt;getContent()</code>
    </FalsableReturnStatement>
  </file>
  <file src="src/Mealz/MealBundle/Controller/MealAdminController.php">
    <InvalidArgument occurrences="1">
      <code>$dateTimeModifier</code>
    </InvalidArgument>
    <InvalidScalarArgument occurrences="4">
      <code>$dateTime-&gt;format('W')</code>
      <code>$dateTime-&gt;format('o')</code>
      <code>$modifiedDateTime-&gt;format('W')</code>
      <code>$modifiedDateTime-&gt;format('o')</code>
    </InvalidScalarArgument>
    <UndefinedInterfaceMethod occurrences="2">
      <code>isClicked</code>
      <code>isClicked</code>
    </UndefinedInterfaceMethod>
  </file>
  <file src="src/Mealz/MealBundle/Entity/Dish.php">
    <InvalidNullableReturnType occurrences="1">
      <code>string</code>
    </InvalidNullableReturnType>
    <NullableReturnStatement occurrences="1">
      <code>$this-&gt;title_de</code>
    </NullableReturnStatement>
  </file>
  <file src="src/Mealz/MealBundle/Entity/ParticipantRepository.php">
    <TooManyArguments occurrences="2">
      <code>orX</code>
      <code>where</code>
    </TooManyArguments>
  </file>
  <file src="src/Mealz/MealBundle/Form/DataTransformer/EntityToIdTransformer.php">
    <ParamNameMismatch occurrences="2">
      <code>$entity</code>
      <code>$identifier</code>
    </ParamNameMismatch>
  </file>
  <file src="src/Mealz/MealBundle/Form/DataTransformer/ProfileToStringTransformer.php">
    <MoreSpecificImplementedParamType occurrences="1">
      <code>$value</code>
    </MoreSpecificImplementedParamType>
  </file>
  <file src="src/Mealz/MealBundle/Form/MealAdmin/MealForm.php">
    <TypeDoesNotContainNull occurrences="1">
      <code>null === $meal-&gt;getDateTime()</code>
    </TypeDoesNotContainNull>
  </file>
  <file src="src/Mealz/MealBundle/Form/Type/DishSelectorCreatorType.php">
    <UndefinedClass occurrences="1">
      <code>DishStringToValuesTransformer</code>
    </UndefinedClass>
  </file>
  <file src="src/Mealz/MealBundle/Service/Doorman.php">
    <UndefinedInterfaceMethod occurrences="3">
      <code>getProfile</code>
    </UndefinedInterfaceMethod>
  </file>
  <file src="src/Mealz/MealBundle/Service/Link.php">
    <NullArgument occurrences="1">
      <code>$action</code>
    </NullArgument>
  </file>
  <file src="src/Mealz/MealBundle/Service/Workday.php">
    <InvalidScalarArgument occurrences="1">
      <code>$year</code>
    </InvalidScalarArgument>
  </file>
  <file src="src/Mealz/MealBundle/Tests/AbstractDatabaseTestCase.php">
    <InvalidNullableReturnType occurrences="1">
      <code>Registry</code>
    </InvalidNullableReturnType>
    <NullableReturnStatement occurrences="1">
      <code>static::$kernel-&gt;getContainer()-&gt;get('doctrine')</code>
    </NullableReturnStatement>
  </file>
  <file src="src/Mealz/MealBundle/Tests/Controller/AbstractControllerTestCase.php">
    <ImplicitToStringCast occurrences="1">
      <code>$user-&gt;getRoles()</code>
    </ImplicitToStringCast>
  </file>
  <file src="src/Mealz/MealBundle/Tests/Controller/CategoryControllerTest.php">
    <InvalidArrayOffset occurrences="1">
      <code>$form['category']['category']</code>
    </InvalidArrayOffset>
  </file>
  <file src="src/Mealz/MealBundle/Tests/Controller/DishVariationControllerTest.php">
    <InvalidArgument occurrences="1">
      <code>$host</code>
    </InvalidArgument>
    <InvalidNullableReturnType occurrences="1">
      <code>DishVariation</code>
    </InvalidNullableReturnType>
    <InvalidOperand occurrences="1">
      <code>$dishId</code>
    </InvalidOperand>
    <InvalidReturnStatement occurrences="1">
      <code>$dishId</code>
    </InvalidReturnStatement>
    <InvalidReturnType occurrences="1">
      <code>Crawler</code>
    </InvalidReturnType>
    <NullableReturnStatement occurrences="1">
      <code>$dishVariation</code>
    </NullableReturnStatement>
    <RedundantCondition occurrences="3">
      <code>count($result)</code>
      <code>is_array($result)</code>
      <code>is_array($result) &amp;&amp; count($result)</code>
    </RedundantCondition>
  </file>
  <file src="src/Mealz/MealBundle/Tests/Controller/MealControllerTest.php">
    <UndefinedInterfaceMethod occurrences="1">
      <code>getOutdatedMeals</code>
    </UndefinedInterfaceMethod>
    <UndefinedMethod occurrences="1">
      <code>$form['invitation_form[day][meals]']</code>
    </UndefinedMethod>
  </file>
  <file src="src/Mealz/MealBundle/Tests/Controller/ParticipantControllerTest.php">
    <UndefinedInterfaceMethod occurrences="1">
      <code>getOutdatedMeals</code>
    </UndefinedInterfaceMethod>
  </file>
  <file src="src/Mealz/MealBundle/Tests/Service/AbstractParticipationServiceTest.php">
    <TooManyArguments occurrences="2">
      <code>willReturn</code>
      <code>willReturn</code>
    </TooManyArguments>
  </file>
  <file src="src/Mealz/MealBundle/Twig/Extension/Doorman.php">
    <LessSpecificImplementedReturnType occurrences="1">
      <code>array</code>
    </LessSpecificImplementedReturnType>
    <TooManyArguments occurrences="1">
      <code>isOfferAvailable</code>
    </TooManyArguments>
  </file>
  <file src="src/Mealz/MealBundle/Validator/Constraints/DishConstraintValidator.php">
    <ParamNameMismatch occurrences="1">
      <code>$entity</code>
    </ParamNameMismatch>
    <TooManyArguments occurrences="1">
      <code>flush</code>
    </TooManyArguments>
  </file>
  <file src="src/Mealz/UserBundle/DataFixtures/ORM/LoadAnonymousUsers.php">
    <UndefinedInterfaceMethod occurrences="2">
      <code>getConnection</code>
      <code>getConnection</code>
    </UndefinedInterfaceMethod>
  </file>
  <file src="src/Mealz/UserBundle/Tests/Service/OAuthProviderTest.php">
    <TooManyArguments occurrences="5">
      <code>willReturn</code>
      <code>willReturn</code>
      <code>willReturn</code>
      <code>willReturn</code>
      <code>willReturn</code>
    </TooManyArguments>
  </file>
  <file src="src/Resources/node_modules/flatted/php/flatted.php">
    <UndefinedPropertyFetch occurrences="2">
      <code>$value-&gt;value</code>
      <code>$value-&gt;value</code>
    </UndefinedPropertyFetch>
    <UndefinedThisPropertyAssignment occurrences="1">
      <code>$this-&gt;value</code>
    </UndefinedThisPropertyAssignment>
  </file>
</files>
